identity_containers/__init__.py
identity_containers/identity_default_dict.py
identity_containers/identity_dict.py
identity_containers/identity_set.py
identity_containers-1.0.2.dist-info/LICENSE
identity_containers-1.0.2.dist-info/WHEEL
identity_containers-1.0.2.dist-info/METADATA
identity_containers-1.0.2.dist-info/RECORD
