Metadata-Version: 2.3
Name: identity-containers
Version: 1.0.2
Summary: Dicts and Sets that hash items based on identity instead of value
Author: Paul Pinterits
Requires-Python: >=3.9
Requires-Dist: typing-extensions
Requires-Dist: pytest ; extra == "dev"
Requires-Dist: pytest-cov ; extra == "dev"
Provides-Extra: dev
